MANIFEST.in
README.rst
setup.py
doc/Makefile
doc/__init__.py
doc/conf.py
doc/copying.rst
doc/index.rst
doc/langacore.kit.django.cache.rst
doc/langacore.kit.django.choices.rst
doc/langacore.kit.django.common.forms.rst
doc/langacore.kit.django.common.middleware.rst
doc/langacore.kit.django.common.models.rst
doc/langacore.kit.django.common.templatetags.bbcode.rst
doc/langacore.kit.django.common.templatetags.converters.rst
doc/langacore.kit.django.common.templatetags.strings.rst
doc/langacore.kit.django.filters.rst
doc/langacore.kit.django.profile.models.rst
doc/make.bat
doc/overview.rst
doc/todo.rst
doc/theme/ADCtheme/LICENSE
doc/theme/ADCtheme/README.rst
doc/theme/ADCtheme/layout.html
doc/theme/ADCtheme/theme.conf
doc/theme/ADCtheme/static/adctheme.css
doc/theme/ADCtheme/static/breadcrumb_background.png
doc/theme/ADCtheme/static/documentation.png
doc/theme/ADCtheme/static/header_sm_mid.png
doc/theme/ADCtheme/static/scrn1.png
doc/theme/ADCtheme/static/scrn2.png
doc/theme/ADCtheme/static/searchfield_leftcap.png
doc/theme/ADCtheme/static/searchfield_repeat.png
doc/theme/ADCtheme/static/searchfield_rightcap.png
doc/theme/ADCtheme/static/title_background.png
doc/theme/ADCtheme/static/toc.js
doc/theme/ADCtheme/static/triangle_closed.png
doc/theme/ADCtheme/static/triangle_left.png
doc/theme/ADCtheme/static/triangle_open.png
src/langacore/__init__.py
src/langacore.kit.django.egg-info/PKG-INFO
src/langacore.kit.django.egg-info/SOURCES.txt
src/langacore.kit.django.egg-info/dependency_links.txt
src/langacore.kit.django.egg-info/namespace_packages.txt
src/langacore.kit.django.egg-info/not-zip-safe
src/langacore.kit.django.egg-info/requires.txt
src/langacore.kit.django.egg-info/top_level.txt
src/langacore/kit/__init__.py
src/langacore/kit/django/__init__.py
src/langacore/kit/django/cache.py
src/langacore/kit/django/choices.py
src/langacore/kit/django/current_dir_support.py
src/langacore/kit/django/filters.py
src/langacore/kit/django/helpers.py
src/langacore/kit/django/metaclasses.py
src/langacore/kit/django/namespace_package_support.py
src/langacore/kit/django/profile_support.py
src/langacore/kit/django/common/__init__.py
src/langacore/kit/django/common/choices.py
src/langacore/kit/django/common/exceptions.py
src/langacore/kit/django/common/forms.py
src/langacore/kit/django/common/middleware.py
