Metadata-Version: 1.0
Name: langacore.kit.django
Version: 0.3.3
Summary: Various common Django-related routines.
Home-page: http://packages.python.org/langacore.kit.django/
Author: LangaCore, Lukasz Langa
Author-email: support@langacore.org, lukasz@langa.pl
License: GPL v3
Platform: any
Classifier: Development Status :: 3 - Alpha
Classifier: Framework :: Django
Classifier: Intended Audience :: Developers
Classifier: License :: OSI Approved :: GNU General Public License (GPL)
Classifier: Natural Language :: English
Classifier: Operating System :: POSIX
Classifier: Operating System :: MacOS :: MacOS X
Classifier: Operating System :: Microsoft :: Windows :: Windows NT/2000
Classifier: Programming Language :: Python
Classifier: Programming Language :: Python :: 2.7
Classifier: Topic :: Internet :: WWW/HTTP
Classifier: Topic :: Software Development :: Libraries :: Python Modules
